README.md
setup.py
ipython_pylint/__init__.py
ipython_pylint/linter.py
ipython_pylint/magic.py
ipython_pylint.egg-info/PKG-INFO
ipython_pylint.egg-info/SOURCES.txt
ipython_pylint.egg-info/dependency_links.txt
ipython_pylint.egg-info/requires.txt
ipython_pylint.egg-info/top_level.txt